{
  "month": 2,
  "day": 11,
  "zodiac": "水瓶座",
  "keyword": "革新の先駆者",
  "personality": "水瓶座の中でも特に独創的で、既成概念を打ち破る力に満ちた人物です。直感と論理のバランスが優れており、人間関係では距離を保ちながらも深い洞察力で周囲を理解します。自由を何より大切にし、型にはまった生活を嫌います。個性的な魅力で多くの人を惹きつけます。",
  "love": "相手の個性を尊重し、束縛されない関係を求めます。知的な会話が恋愛の重要な要素。感情的というより理性的なアプローチをとり、パートナーとの精神的な繋がりを最優先にします。",
  "work": "新規事業開発やIT分野での活躍が顕著です。創造的問題解決と革新的なアイデア提案が得意。チームプレイより独立心が強く、自分のペースで進める環境で最高の成果を発揮できます。",
  "money": "金銭には淡泊ながら、未来投資への嗅覚は鋭敏。計画的な資産運用よりも、新しい分野への挑戦的な投資に向きがあります。経済的自由を求める傾向が強いです。",
  "luckyColor": "銀色",
  "luckyNumber": 7,
  "luckyItem": "眼鏡",
  "compatibleZodiac": "双子座、天秤座、獅子座",
  "yearFortune": "2026年は転機の年です。これまでの準備が実を結び、新たな可能性が次々と開かれます。特に上半期は対人関係で重要な出会いがあり、その選択が人生の方向性を大きく変える可能性があります。自分の直感を信じ、未知への一歩を恐れず踏み出すことが成功の鍵です。下半期は成果の収穫期となるでしょう。"
}