{
  "month": 5,
  "day": 6,
  "zodiac": "牡牛座",
  "keyword": "確実な歩み",
  "personality": "5月6日生まれは、牡牛座の中でも特に実行力と堅実性に優れた人物です。夢を描くだけでなく、それを確実に形にする力を持っています。穏やかで落ち着いた雰囲気を醸し出しながらも、内には強い意志と忍耐力を秘めています。周囲の信頼も厚く、頼られることが多いでしょう。",
  "love": "恋愛では相手をしっかり見つめ、信頼できる関係を築くことを重視します。派手さより深い絆を求め、長く寄り添える相手を選びます。一度決めたら貫き通す誠実さで、相手に安定感を与えます。",
  "work": "計画性と実行力を活かし、プロジェクト管理や営業企画などで活躍します。コツコツと成果を積み上げるタイプで、長期的な目標達成に向いています。信頼性の高さから、責任ある立場を任されることが多いでしょう。",
  "money": "金銭管理に優れ、浪費癖は少ないタイプです。着実に資産を増やすことに向いており、長期投資や貯蓄で成功します。ただし時には柔軟性を持ち、必要な投資にも目を向けましょう。",
  "luckyColor": "緑",
  "luckyNumber": 6,
  "luckyItem": "羅針盤",
  "compatibleZodiac": "乙女座・山羊座",
  "yearFortune": "2026年はあなたの成長の年です。これまでの努力が花開き、新しいステージへの扉が開きます。特に上半期は対人関係の充実に注目。信頼できるパートナーシップが運を引き寄せます。下半期は経済面での向上が期待でき、大切な決断を下す良い時期です。迷わず前に進みましょう。"
}