{
  "slug1": "leo",
  "slug2": "cancer",
  "name1": "獅子座",
  "name2": "蟹座",
  "score": 58,
  "keyword": "情熱と優しさの調和",
  "summary": "獅子座の情熱的で大胆な性質と、蟹座の感情的で慎重な性質が対照的な組み合わせです。獅子座の明るさが蟹座を励まし、蟹座の深い愛情が獅子座を落ち着かせる可能性があります。相互理解と歩み寄りが相性を高めるカギとなります。",
  "love": "獅子座のロマンティックで情熱的な愛情表現と、蟹座の深くて献身的な愛情が相補関係を築けます。ただし獅子座の自由さと蟹座の執着心の違いを理解し、コミュニケーションを大切にすることが重要です。",
  "friendship": "獅子座の社交性と蟹座の思いやりが調和した友情になります。獅子座は蟹座に新しい世界を見せ、蟹座は獅子座に心の安定をもたらします。互いに相手の違いを尊重することで深い絆が生まれます。",
  "work": "獅子座のリーダーシップと蟹座の細やかな気配りで仕事の相性は良好です。獅子座が進むべき方向を示し、蟹座が細部に目を配ることで強力なパートナーシップが実現します。信頼関係の構築が成功の鍵です。",
  "strength": "獅子座の大胆さと蟹座の慎重さが相互補完し、バランスの取れた判断ができます。互いに異なる視点を持つため、問題解決の幅が広がります。",
  "challenge": "獅子座の派手さと蟹座の内向性、獅子座の独立心と蟹座の依存心の違いに注意が必要です。すれ違いやストレスが生じやすいため、対話が不可欠です。",
  "advice": "相手の違いを受け入れ、尊重することが大切です。獅子座は蟹座の感情的ニーズに耳を傾け、蟹座は獅子座の自由を認めましょう。定期的な対話で理解を深めることが相性向上につながります。"
}