{
  "slug1": "pisces",
  "slug2": "libra",
  "name1": "魚座",
  "name2": "天秤座",
  "score": 72,
  "keyword": "優雅で深い精神的絆",
  "summary": "魚座の深い感受性と天秤座の知性が調和する相性です。天秤座は魚座の曖昧さを整理し、魚座は天秤座に情感をもたらします。互いに異なる視点が補完し合い、精神的な成長をもたらします。ただし、決断力の違いが課題となる可能性があります。",
  "love": "魚座の浪漫性と天秤座の優雅さが美しく融合します。天秤座は魚座を理解し、魚座は天秤座に深い愛情をもたらします。しかし魚座の感情的波動と天秤座の論理性のギャップが時に衝突することがあります。",
  "friendship": "二人は知的で精神的な友情を築けます。天秤座は社交的、魚座は思慮深く、互いに異なる友人グループをもたらします。共通の興味である芸術や人道支援を通じて、深い信頼関係が形成されます。",
  "work": "天秤座の戦略性と魚座の創造性が仕事で相乗効果を生みます。天秤座が計画を立て、魚座が革新的なアイデアを提供します。ただし魚座の締め切り管理と天秤座の優柔不断さが課題となる可能性があります。",
  "strength": "知性と感受性の完全なバランス。互いに欠ける部分を補完し、精神的な深さと社交的優雅さを兼ね備えた関係になります。",
  "challenge": "決断の速度と方法が異なります。魚座は直感的、天秤座は分析的なため、判断の過程で摩擦が生じやすいです。感情と理性のズレを理解する必要があります。",
  "advice": "互いの違いを尊重し、補完関係として活かしましょう。魚座は天秤座の視点から学び、天秤座は魚座の感受性を大切にすることで、より強い絆が築けます。コミュニケーションが鍵です。"
}